AUTHORS.rst
CONTRIBUTING.rst
HISTORY.rst
LICENSE
MANIFEST.in
README.rst
setup.cfg
setup.py
docs/Makefile
docs/authors.rst
docs/conf.py
docs/contributing.rst
docs/history.rst
docs/index.rst
docs/installation.rst
docs/make.bat
docs/readme.rst
docs/usage.rst
lasagne_visualizer/__init__.py
lasagne_visualizer/lasagne_visualizer.py
lasagne_visualizer.egg-info/PKG-INFO
lasagne_visualizer.egg-info/SOURCES.txt
lasagne_visualizer.egg-info/dependency_links.txt
lasagne_visualizer.egg-info/not-zip-safe
lasagne_visualizer.egg-info/requires.txt
lasagne_visualizer.egg-info/top_level.txt
tests/__init__.py
tests/tests.py