Metadata-Version: 1.1
Name: lasagne-visualizer
Version: 0.1.0
Summary: A tiny package to enable live-visualization of weight learning using lasagne models in ipython notebook.
Home-page: https://github.com/SimonKohl/lasagne_visualizer
Author: Simon Kohl
Author-email: simon.kohl@dkfz.de
License: MIT license
Keywords: lasagne_visualizer
Platform: UNKNOWN
Classifier: Development Status :: 2 - Pre-Alpha
Classifier: Intended Audience :: Developers
Classifier: License :: OSI Approved :: MIT License
Classifier: Natural Language :: English
Classifier: Programming Language :: Python :: 2.7
